{
    "426028646": {
        "Tweets": [
            {
                "lastActiveAtSeconds": 1534881592, 
                "promotedMetadata": {
                    "advertiserId": 426028646, 
                    "political": false
                }, 
                "serveable": false, 
                "id": 1029163369679413248, 
                "tweetId": "1029163369679413248"
            }, 
            {
                "lastActiveAtSeconds": 1534881592, 
                "promotedMetadata": {
                    "advertiserId": 426028646, 
                    "political": false
                }, 
                "serveable": true, 
                "id": 1005167890687918081, 
                "tweetId": "1005167890687918081"
            }, 
            {
                "lastActiveAtSeconds": 1534881592, 
                "promotedMetadata": {
                    "advertiserId": 426028646, 
                    "political": false
                }, 
                "serveable": true, 
                "id": 1021636460397490176, 
                "tweetId": "1021636460397490176"
            }, 
            {
                "lastActiveAtSeconds": 1534881592, 
                "promotedMetadata": {
                    "advertiserId": 426028646, 
                    "political": false
                }, 
                "serveable": true, 
                "id": 1022912511211913221, 
                "tweetId": "1022912511211913221"
            }, 
            {
                "lastActiveAtSeconds": 1534881592, 
                "promotedMetadata": {
                    "advertiserId": 426028646, 
                    "political": false
                }, 
                "serveable": true, 
                "id": 1022912572801077248, 
                "tweetId": "1022912572801077248"
            }, 
            {
                "lastActiveAtSeconds": 1534881592, 
                "promotedMetadata": {
                    "advertiserId": 426028646, 
                    "political": false
                }, 
                "serveable": true, 
                "id": 1027324338528182272, 
                "tweetId": "1027324338528182272"
            }, 
            {
                "lastActiveAtSeconds": 1534881592, 
                "promotedMetadata": {
                    "advertiserId": 426028646, 
                    "political": false
                }, 
                "serveable": true, 
                "id": 1027324394815643649, 
                "tweetId": "1027324394815643649"
            }, 
            {
                "lastActiveAtSeconds": 1534881592, 
                "promotedMetadata": {
                    "advertiserId": 426028646, 
                    "political": false
                }, 
                "serveable": true, 
                "id": 1028735710755479553, 
                "tweetId": "1028735710755479553"
            }, 
            {
                "lastActiveAtSeconds": 1534881592, 
                "promotedMetadata": {
                    "advertiserId": 426028646, 
                    "political": false
                }, 
                "serveable": true, 
                "id": 1029162765699579905, 
                "tweetId": "1029162765699579905"
            }, 
            {
                "lastActiveAtSeconds": 1534881592, 
                "promotedMetadata": {
                    "advertiserId": 426028646, 
                    "political": false
                }, 
                "serveable": true, 
                "id": 1029163208068685824, 
                "tweetId": "1029163208068685824"
            }, 
            {
                "lastActiveAtSeconds": 1534881592, 
                "promotedMetadata": {
                    "advertiserId": 426028646, 
                    "political": false
                }, 
                "serveable": true, 
                "id": 1029163317426671616, 
                "tweetId": "1029163317426671616"
            }, 
            {
                "lastActiveAtSeconds": 1534881592, 
                "promotedMetadata": {
                    "advertiserId": 426028646, 
                    "political": false
                }, 
                "serveable": true, 
                "id": 1029798674249871361, 
                "tweetId": "1029798674249871361"
            }, 
            {
                "lastActiveAtSeconds": 1534881592, 
                "promotedMetadata": {
                    "advertiserId": 426028646, 
                    "political": false
                }, 
                "serveable": false, 
                "id": 1031949130875265025, 
                "tweetId": "1031949130875265025"
            }, 
            {
                "lastActiveAtSeconds": 1534881592, 
                "promotedMetadata": {
                    "advertiserId": 426028646, 
                    "political": false
                }, 
                "serveable": true, 
                "id": 1031949203432464384, 
                "tweetId": "1031949203432464384"
            }, 
            {
                "lastActiveAtSeconds": 1534881592, 
                "promotedMetadata": {
                    "advertiserId": 426028646, 
                    "political": false
                }, 
                "serveable": true, 
                "id": 1031950058655297536, 
                "tweetId": "1031950058655297536"
            }
        ], 
        "ScreenName": "JohnKDelaney"
    }
}