[{"UserScreenName": "BetoORourke", "tweetID": "1025016704546484224", "UserID": "342863309", "metadata": [{"usd_spend": 9828.770772, "start_timestamp": 1533215585, "account_id": "18ce54qh4jc", "tweet_count": 8, "tailored_audience_used": false, "political_disclaimer": {"organization": "Beto for Texas", "sponsorshipType": "Direct"}, "impressions": 598724, "line_item_id": "c756k", "end_timestamp": 1533787140}]}, {"UserScreenName": "BetoORourke", "tweetID": "1025042395031851012", "UserID": "342863309", "metadata": [{"usd_spend": 12554.874116, "start_timestamp": 1533215585, "account_id": "18ce54qh4jc", "tweet_count": 8, "tailored_audience_used": false, "political_disclaimer": {"organization": "Beto for Texas", "sponsorshipType": "Direct"}, "impressions": 693023, "line_item_id": "c756y", "end_timestamp": 1533787140}]}, {"UserScreenName": "BetoORourke", "tweetID": "1025042349272039425", "UserID": "342863309", "metadata": [{"usd_spend": 12554.874116, "start_timestamp": 1533215585, "account_id": "18ce54qh4jc", "tweet_count": 8, "tailored_audience_used": false, "political_disclaimer": {"organization": "Beto for Texas", "sponsorshipType": "Direct"}, "impressions": 693023, "line_item_id": "c756y", "end_timestamp": 1533787140}]}, {"UserScreenName": "BetoORourke", "tweetID": "1025042217591812096", "UserID": "342863309", "metadata": [{"usd_spend": 12554.874116, "start_timestamp": 1533215585, "account_id": "18ce54qh4jc", "tweet_count": 8, "tailored_audience_used": false, "political_disclaimer": {"organization": "Beto for Texas", "sponsorshipType": "Direct"}, "impressions": 693023, "line_item_id": "c756y", "end_timestamp": 1533787140}]}, {"UserScreenName": "BetoORourke", "tweetID": "1025042127821135873", "UserID": "342863309", "metadata": [{"usd_spend": 12554.874116, "start_timestamp": 1533215585, "account_id": "18ce54qh4jc", "tweet_count": 8, "tailored_audience_used": false, "political_disclaimer": {"organization": "Beto for Texas", "sponsorshipType": "Direct"}, "impressions": 693023, "line_item_id": "c756y", "end_timestamp": 1533787140}]}, {"UserScreenName": "BetoORourke", "tweetID": "1025042073743966208", "UserID": "342863309", "metadata": [{"usd_spend": 9828.770772, "start_timestamp": 1533215585, "account_id": "18ce54qh4jc", "tweet_count": 8, "tailored_audience_used": false, "political_disclaimer": {"organization": "Beto for Texas", "sponsorshipType": "Direct"}, "impressions": 598724, "line_item_id": "c756k", "end_timestamp": 1533787140}]}, {"UserScreenName": "BetoORourke", "tweetID": "1025042023773036546", "UserID": "342863309", "metadata": [{"usd_spend": 9828.770772, "start_timestamp": 1533215585, "account_id": "18ce54qh4jc", "tweet_count": 8, "tailored_audience_used": false, "political_disclaimer": {"organization": "Beto for Texas", "sponsorshipType": "Direct"}, "impressions": 598724, "line_item_id": "c756k", "end_timestamp": 1533787140}]}, {"UserScreenName": "BetoORourke", "tweetID": "1025041974322257920", "UserID": "342863309", "metadata": [{"usd_spend": 9834.46343, "start_timestamp": 1533215585, "account_id": "18ce54qh4jc", "tweet_count": 8, "tailored_audience_used": false, "political_disclaimer": {"organization": "Beto for Texas", "sponsorshipType": "Direct"}, "impressions": 598825, "line_item_id": "c756k", "end_timestamp": 1533787140}]}, {"UserScreenName": "BetoORourke", "tweetID": "1025041917598474240", "UserID": "342863309", "metadata": [{"usd_spend": 9834.46343, "start_timestamp": 1533215585, "account_id": "18ce54qh4jc", "tweet_count": 8, "tailored_audience_used": false, "political_disclaimer": {"organization": "Beto for Texas", "sponsorshipType": "Direct"}, "impressions": 598825, "line_item_id": "c756k", "end_timestamp": 1533787140}]}, {"UserScreenName": "BetoORourke", "tweetID": "1025017130708688896", "UserID": "342863309", "metadata": [{"usd_spend": 12554.874116, "start_timestamp": 1533215585, "account_id": "18ce54qh4jc", "tweet_count": 8, "tailored_audience_used": false, "political_disclaimer": {"organization": "Beto for Texas", "sponsorshipType": "Direct"}, "impressions": 693073, "line_item_id": "c756y", "end_timestamp": 1533787140}]}, {"UserScreenName": "BetoORourke", "tweetID": "1025017087423537152", "UserID": "342863309", "metadata": [{"usd_spend": 12554.874116, "start_timestamp": 1533215585, "account_id": "18ce54qh4jc", "tweet_count": 8, "tailored_audience_used": false, "political_disclaimer": {"organization": "Beto for Texas", "sponsorshipType": "Direct"}, "impressions": 693073, "line_item_id": "c756y", "end_timestamp": 1533787140}]}, {"UserScreenName": "BetoORourke", "tweetID": "1025017040686342144", "UserID": "342863309", "metadata": [{"usd_spend": 12554.874116, "start_timestamp": 1533215585, "account_id": "18ce54qh4jc", "tweet_count": 8, "tailored_audience_used": false, "political_disclaimer": {"organization": "Beto for Texas", "sponsorshipType": "Direct"}, "impressions": 693073, "line_item_id": "c756y", "end_timestamp": 1533787140}]}, {"UserScreenName": "BetoORourke", "tweetID": "1025017006733516800", "UserID": "342863309", "metadata": [{"usd_spend": 12554.874116, "start_timestamp": 1533215585, "account_id": "18ce54qh4jc", "tweet_count": 8, "tailored_audience_used": false, "political_disclaimer": {"organization": "Beto for Texas", "sponsorshipType": "Direct"}, "impressions": 693073, "line_item_id": "c756y", "end_timestamp": 1533787140}]}, {"UserScreenName": "BetoORourke", "tweetID": "1025016917956816899", "UserID": "342863309", "metadata": [{"usd_spend": 9834.46343, "start_timestamp": 1533215585, "account_id": "18ce54qh4jc", "tweet_count": 8, "tailored_audience_used": false, "political_disclaimer": {"organization": "Beto for Texas", "sponsorshipType": "Direct"}, "impressions": 598825, "line_item_id": "c756k", "end_timestamp": 1533787140}]}, {"UserScreenName": "BetoORourke", "tweetID": "1025016829142417408", "UserID": "342863309", "metadata": [{"usd_spend": 9834.46343, "start_timestamp": 1533215585, "account_id": "18ce54qh4jc", "tweet_count": 8, "tailored_audience_used": false, "political_disclaimer": {"organization": "Beto for Texas", "sponsorshipType": "Direct"}, "impressions": 598825, "line_item_id": "c756k", "end_timestamp": 1533787140}]}, {"UserScreenName": "BetoORourke", "tweetID": "1025016763732262912", "UserID": "342863309", "metadata": [{"usd_spend": 9834.46343, "start_timestamp": 1533215585, "account_id": "18ce54qh4jc", "tweet_count": 8, "tailored_audience_used": false, "political_disclaimer": {"organization": "Beto for Texas", "sponsorshipType": "Direct"}, "impressions": 598825, "line_item_id": "c756k", "end_timestamp": 1533787140}]}, {"UserScreenName": "BetoORourke", "tweetID": "1025042779095871490", "UserID": "342863309", "metadata": [{"usd_spend": 21351.569193, "start_timestamp": 1533219539, "account_id": "18ce54qh4jc", "tweet_count": 8, "tailored_audience_used": false, "political_disclaimer": {"organization": "Beto for Texas", "sponsorshipType": "Direct"}, "impressions": 1554331, "line_item_id": "c75qw", "end_timestamp": 1533959940}]}, {"UserScreenName": "BetoORourke", "tweetID": "1025042825434615808", "UserID": "342863309", "metadata": [{"usd_spend": 21351.569193, "start_timestamp": 1533219539, "account_id": "18ce54qh4jc", "tweet_count": 8, "tailored_audience_used": false, "political_disclaimer": {"organization": "Beto for Texas", "sponsorshipType": "Direct"}, "impressions": 1554331, "line_item_id": "c75qw", "end_timestamp": 1533959940}]}, {"UserScreenName": "BetoORourke", "tweetID": "1025025851665080321", "UserID": "342863309", "metadata": [{"usd_spend": 21351.569193, "start_timestamp": 1533219539, "account_id": "18ce54qh4jc", "tweet_count": 8, "tailored_audience_used": false, "political_disclaimer": {"organization": "Beto for Texas", "sponsorshipType": "Direct"}, "impressions": 1554331, "line_item_id": "c75qw", "end_timestamp": 1533959940}]}, {"UserScreenName": "BetoORourke", "tweetID": "1025025891351576576", "UserID": "342863309", "metadata": [{"usd_spend": 21351.569193, "start_timestamp": 1533219539, "account_id": "18ce54qh4jc", "tweet_count": 8, "tailored_audience_used": false, "political_disclaimer": {"organization": "Beto for Texas", "sponsorshipType": "Direct"}, "impressions": 1554331, "line_item_id": "c75qw", "end_timestamp": 1533959940}]}]